LICENSE
MANIFEST.in
README.rst
requirements.txt
setup.py
django_filemaker.egg-info/PKG-INFO
django_filemaker.egg-info/SOURCES.txt
django_filemaker.egg-info/dependency_links.txt
django_filemaker.egg-info/requires.txt
django_filemaker.egg-info/top_level.txt
filemaker/__init__.py
filemaker/base.py
filemaker/conf.py
filemaker/exceptions.py
filemaker/fields.py
filemaker/manager.py
filemaker/models.py
filemaker/parser.py
filemaker/tests.py
filemaker/utils.py
filemaker/validators.py
test_project/__init__.py
test_project/settings.py
test_project/urls.py
test_project/wsgi.py