Metadata-Version: 1.1
Name: django-filemaker
Version: 0.2.2
Summary: FileMaker access and integration with Django
Home-page: http://github.com/TitanEntertainmentGroup/django-filemaker
Author: Luke Pomfrey
Author-email: luke.pomfrey@titanemail.com
License: BSD
Platform: UNKNOWN
Classifier: Development Status :: 4 - Beta
Classifier: Environment :: Web Environment
Classifier: Framework :: Django
Classifier: Intended Audience :: Developers
Classifier: License :: OSI Approved :: BSD License
Classifier: Operating System :: OS Independent
Classifier: Programming Language :: Python
Classifier: Topic :: Internet :: WWW/HTTP
